{
    "header": {
        "target": "w",
        "formatVersion": 5,
        "hidef": true,
        "compressed": 128
    },
    "readers": [
        {
            "type": "Microsoft.Xna.Framework.Content.DictionaryReader`2[[System.Int32, mscorlib, Version=4.0.0.0, Culture=neutral, PublicKeyToken=b77a5c561934e089],[System.Int32[], mscorlib, Version=4.0.0.0, Culture=neutral, PublicKeyToken=b77a5c561934e089]]",
            "version": 0
        },
        {
            "type": "Microsoft.Xna.Framework.Content.Int32Reader",
            "version": 0
        },
        {
            "type": "Microsoft.Xna.Framework.Content.ArrayReader`1[[System.Int32, mscorlib, Version=4.0.0.0, Culture=neutral, PublicKeyToken=b77a5c561934e089]]",
            "version": 0
        }
    ],
    "content": {
        "1000": [
            2,
            2,
            -2,
            5,
            1,
            0
        ],
        "1400": [
            0,
            0,
            1,
            5,
            0
        ],
        "1630": [
            2,
            3,
            1,
            0,
            5,
            8,
            1
        ]
    }
}